django_future_tasks/__init__.py
django_future_tasks/admin.py
django_future_tasks/apps.py
django_future_tasks/fields.py
django_future_tasks/handlers.py
django_future_tasks/models.py
django_future_tasks/management/__init__.py
django_future_tasks/management/commands/__init__.py
django_future_tasks/management/commands/populate_periodic_future_tasks.py
django_future_tasks/management/commands/process_future_tasks.py
django_future_tasks/migrations/0001_initial.py
django_future_tasks/migrations/0002_periodic_future_task.py
django_future_tasks/migrations/0003_futuretask_execution_time.py
django_future_tasks/migrations/0004_futuretask_status_interrupted.py
django_future_tasks/migrations/0005_periodicfuturetask_max_number_of_executions.py
django_future_tasks/migrations/0006_periodicfuturetask_end_time.py
django_future_tasks/migrations/0007_alter_periodicfuturetask_cron_string.py
django_future_tasks/migrations/__init__.py
django_future_tasks/static/django_future_tasks/cronfield.css
django_future_tasks-1.3.1.dist-info/LICENSE
django_future_tasks-1.3.1.dist-info/METADATA
django_future_tasks-1.3.1.dist-info/WHEEL
django_future_tasks-1.3.1.dist-info/top_level.txt
django_future_tasks-1.3.1.dist-info/RECORD
