Metadata-Version: 2.1
Name: django-future-tasks
Version: 1.3.1
Summary: A library to create periodic, cron-like tasks or single tasks with a specified execution/start time and schedule it to run in the future.
Home-page: https://github.com/anexia/django-future-tasks
Author: Armin Ster
Author-email: aster@anexia-it.com
License: MIT License
Platform: UNKNOWN
Classifier: Development Status :: 5 - Production/Stable
Classifier: Framework :: Django
Classifier: Framework :: Django :: 4.2
Classifier: Framework :: Django :: 5.0
Classifier: Framework :: Django :: 5.1
Classifier: Intended Audience :: Developers
Classifier: License :: OSI Approved :: MIT License
Classifier: Operating System :: OS Independent
Classifier: Programming Language :: Python
Classifier: Programming Language :: Python :: 3
Classifier: Programming Language :: Python :: 3.9
Classifier: Programming Language :: Python :: 3.10
Classifier: Programming Language :: Python :: 3.11
Classifier: Programming Language :: Python :: 3.12
Classifier: Programming Language :: Python :: 3.13
License-File: LICENSE
Requires-Dist: croniter<3.1,>=3.0.3
Requires-Dist: django-cronfield<0.3,>=0.2.0
